{
    "version": 2,
    "type": "full",
    "values": {
        "addons.enabled": ["7tv-emotes", "ffzap-core", "ffzap-bttv", "fs-chat"],
        "p:0:chat.badges.hidden": {
            "m-tcon": true,
            "m-other": true,
            "m-owl": true,
            "m-game": true,
            "m-ffz": true,
            "m-addon-7tv-emotes": true,
            "m-addon-ffzap-bttv": true,
            "m-addon-ffzap-core": true,
            "arcane-season-2-premiere": true,
            "bits-leader": true,
            "clip-the-halls": true,
            "clips-leader": true,
            "chatter-cs-go-2022": true,
            "creator-cs-go-2022": true,
            "dreamcon-2024": true,
            "sub-gift-leader": true,
            "game-developer": true,
            "destiny-2-the-final-shape-streamer": true,
            "destiny-2-final-shape-raid-race": true,
            "founder": true,
            "extension": true,
            "hype-train": true,
            "la-velada-iv": true,
            "gold-pixel-heart": true,
            "moments": true,
            "marathon-reveal-runner": true,
            "gold-pixel-heart---together-for-good-24": true,
            "gone-bananas": true,
            "minecraft-15th-anniversary-celebration": true,
            "predictions": true,
            "clip-champ": true,
            "rplace-2023": true,
            "zevent-2024": true,
            "user-anniversary": true,
            "twitch-recap-2024": true,
            "twitch-recap-2023": true,
            "ambassador": true,
            "twitch-dj": true,
            "twitch-intern-2023": true,
            "twitch-intern-2024": true,
            "the-golden-predictor-of-the-game-awards-2023": true,
            "superultracombo-2023": true,
            "the-game-awards-2023": true,
            "streamer-awards-2024": true,
            "sub-gifter": true,
            "subtember-2024": true,
            "speedons-5-badge": true,
            "ruby-pixel-heart---together-for-good-24": true,
            "share-the-love": true,
            "artist-badge": true,
            "purple-pixel-heart---together-for-good-24": true,
            "premium": true,
            "turbo": true,
            "raging-wolf-helm": true
        }
    }
}
